{"aptos.md":"CGd1Fx4T","bitcoin.md":"0quKHfJL","en_getting-started.md":"83DxCn_D","en_index.md":"DitdouNg","en_release-notes.md":"mwbAVd0x","en_bitcoin.md":"9BjOSVBy","en_evm.md":"L1waTO0N","en_material.md":"fXMUBjAW","en_aptos.md":"2Ugrw_ej","en_solana.md":"P3YWwLze","en_stacks.md":"08m5aaMy","en_sui.md":"BAt7TJIX","en_tron.md":"t22hWKaB","en_ton.md":"y5AHKJa3","material.md":"igGEOt8L","index.md":"96RH8thq","getting-started.md":"3GOkGSGU","release-notes.md":"NA6LcJjt","evm.md":"IeFO6h_x","solana-cn.md":"WDeAIE65","solana-en.md":"M1zToYp8","solana.md":"AYSXYTNj","stacks.md":"hCxxoTn9","tron.md":"TfPHRjKd","sui.md":"sn4djL0f","zh_aptos.md":"LGKa9rgH","zh_getting-started.md":"HR08TEtE","zh_index.md":"ONQdUTTQ","ton.md":"_fCE_tRl","zh_release-notes.md":"00m5tQC3","zh_material.md":"p6Mmk9Dg","zh_evm.md":"72OaTfWu","zh_bitcoin.md":"rFtzwaK4","zh_solana.md":"Lo7Wc1eq","zh_sui.md":"22_91_k0","zh_stacks.md":"Vl_pW522","zh_tron.md":"HQ1U_Hg6","zh_ton.md":"aSKD33ko"}
